qlcp/__init__.py
qlcp/__main__.py
qlcp/bright.param
qlcp/bright.sex
qlcp/default.param
qlcp/default.sex
qlcp/getxy.py
qlcp/j_all.py
qlcp/j_run.py
qlcp/note.md
qlcp/q_biascomb.py
qlcp/q_cali.py
qlcp/q_cata.py
qlcp/q_flatcomb.py
qlcp/q_graph.py
qlcp/q_imgcorr.py
qlcp/q_mklist.py
qlcp/q_offset.py
qlcp/q_phot.py
qlcp/q_pick.py
qlcp/q_sep.py
qlcp/q_wcs.py
qlcp/u_conf.py
qlcp/u_log.py
qlcp/u_utils.py
qlcp/u_workmode.py
qlcp-0.24.913.dist-info/LICENSE
qlcp-0.24.913.dist-info/METADATA
qlcp-0.24.913.dist-info/WHEEL
qlcp-0.24.913.dist-info/top_level.txt
qlcp-0.24.913.dist-info/RECORD
