Metadata-Version: 2.1
Name: qlcp
Version: 0.24.913
Summary: Quick Light Curve Pipeline v2024
Home-page: https://github.com/drjiezheng/qlcp
Author: Dr Jie Zheng & Dr Lin-Qiao Jiang
Author-email: jiezheng@nao.cas.cn
Classifier: Development Status :: 5 - Production/Stable
Classifier: Intended Audience :: Science/Research
Classifier: License :: OSI Approved :: MIT License
Classifier: Operating System :: POSIX
Classifier: Operating System :: MacOS
Classifier: Programming Language :: Python :: 3 :: Only
Classifier: Topic :: Scientific/Engineering :: Physics
Classifier: Topic :: Scientific/Engineering :: Astronomy
Requires-Python: >=3.10
License-File: LICENSE
Requires-Dist: numpy
Requires-Dist: scipy
Requires-Dist: matplotlib
Requires-Dist: astropy
Requires-Dist: tqdm
Requires-Dist: qastutil
Requires-Dist: qmatch
